LICENSE
README.md
setup.cfg
setup.py
mge_graphql/__init__.py
mge_graphql/descriptions.py
mge_graphql/exceptions.py
mge_graphql.egg-info/PKG-INFO
mge_graphql.egg-info/SOURCES.txt
mge_graphql.egg-info/dependency_links.txt
mge_graphql.egg-info/requires.txt
mge_graphql.egg-info/top_level.txt
mge_graphql/mutations/__init__.py
mge_graphql/mutations/base.py
mge_graphql/types/__init__.py
mge_graphql/types/common.py
mge_graphql/utils/__init__.py
mge_graphql/utils/error_codes.py