Metadata-Version: 2.1
Name: mge-graphql
Version: 1.1.0
Summary: GraphQL support with data validations, error handle and permission support built on top of graphene.
Home-page: https://github.com/mgesoftware/mge-graphql
Author: Alexandru Plesoiu
Author-email: alexandru@mgesoftware.com
License: BSD 3-Clause "New" or "Revised"
Keywords: api graphene mongodb flask graphql mge_graphql mge-graphql rest relay mgesoftware mge
Platform: UNKNOWN
Classifier: Development Status :: 3 - Alpha
Classifier: Intended Audience :: Developers
Classifier: Topic :: Software Development :: Libraries
Classifier: Programming Language :: Python :: 3.6
Classifier: Programming Language :: Python :: 3.7
Classifier: Programming Language :: Python :: 3.8
Classifier: Programming Language :: Python :: 3.9
Classifier: Programming Language :: Python :: 3.10
License-File: LICENSE
